mycalc/calculator.py
mycalc/mycalc.py
jgb08191-0.0.1.dist-info/LICENSE
jgb08191-0.0.1.dist-info/METADATA
jgb08191-0.0.1.dist-info/WHEEL
jgb08191-0.0.1.dist-info/top_level.txt
jgb08191-0.0.1.dist-info/RECORD
