Metadata-Version: 2.1
Name: jgb08191
Version: 0.0.1
Summary: nice calculator
Home-page: https://github.com/chunsejin/calc0001
Download-URL: https://github.com/chunsejin/calc0001
Author: dohyun
License-File: LICENSE
